gbqschema_converter/__init__.py
gbqschema_converter/__main__.py
gbqschema_converter/gbqschema_to_jsonschema.py
gbqschema_converter/jsonschema_to_gbqschema.py
gbqschema_converter-1.2.1.dist-info/LICENSE
gbqschema_converter-1.2.1.dist-info/METADATA
gbqschema_converter-1.2.1.dist-info/WHEEL
gbqschema_converter-1.2.1.dist-info/entry_points.txt
gbqschema_converter-1.2.1.dist-info/top_level.txt
gbqschema_converter-1.2.1.dist-info/RECORD
