Metadata-Version: 2.1
Name: gbqschema-converter
Version: 1.2.1
Summary: Library to convert Google BigQuery Table Schema into Json Schema
Home-page: https://github.com/kislerdm/gbqschema_converter
Author: Dmitry Kisler
Author-email: admin@dkisler.com
License: MIT
Platform: UNKNOWN
Classifier: Development Status :: 5 - Production/Stable
Classifier: Programming Language :: Python :: 3
Classifier: Programming Language :: Python :: 3.6
Classifier: Programming Language :: Python :: 3.7
Classifier: Programming Language :: Python :: 3.8
Classifier: License :: OSI Approved :: MIT License
Classifier: Operating System :: OS Independent
Requires-Dist: fastjsonschema (>=2.14.4)
Requires-Dist: google-cloud-bigquery (>=1.24.0)
